wmt/__init__.py
wmt/__main__.py
wmt/common.py
wmt/db.py
wmt/onedrivedb.py
wmt/settings.py
wmt/wmt.py
wmt-0.0.4.dist-info/DESCRIPTION.rst
wmt-0.0.4.dist-info/METADATA
wmt-0.0.4.dist-info/RECORD
wmt-0.0.4.dist-info/WHEEL
wmt-0.0.4.dist-info/entry_points.txt
wmt-0.0.4.dist-info/metadata.json
wmt-0.0.4.dist-info/top_level.txt
