Metadata-Version: 2.0
Name: wmt
Version: 0.0.4
Summary: Where is my time?
Home-page: https://github.com/idanpa/whereismytime
Author: IdanP
Author-email: idan.kp@gmail.com
License: UNKNOWN
Platform: UNKNOWN
Classifier: Programming Language :: Python :: 3
Classifier: License :: OSI Approved :: MIT License
Classifier: Operating System :: OS Independent
Requires-Dist: dateparser
Requires-Dist: onedrivesdk
